uml_django/__init__.py
uml_django/inspect.py
uml_django-1.0.4.dist-info/LICENSE.txt
uml_django-1.0.4.dist-info/METADATA
uml_django-1.0.4.dist-info/WHEEL
uml_django-1.0.4.dist-info/RECORD
