Metadata-Version: 2.1
Name: uml_django
Version: 1.0.4
Summary: A UML Generator for Django and Django Rest Framework projects
Home-page: https://github.com/Pedro-V8/uml-django
Author: Pedro Vieira
Author-email: pedrophdv@outlook.com
Requires-Python: >=3.8,<4.0
Classifier: Programming Language :: Python :: 3
Classifier: Programming Language :: Python :: 3.8
Classifier: Programming Language :: Python :: 3.9
Classifier: Programming Language :: Python :: 3.10
Classifier: Programming Language :: Python :: 3.11
Classifier: Programming Language :: Python :: 3.12
Requires-Dist: django (>=4.2.7,<5.0.0)
Requires-Dist: plantuml (>=0.3.0,<0.4.0)
Requires-Dist: six (>=1.16.0,<2.0.0)
Project-URL: Repository, https://github.com/Pedro-V8/uml-django
